resourcespace_cli/__init__.py
resourcespace_cli/client.py
resourcespace_cli/config.py
resourcespace_cli/exceptions.py
resourcespace_cli/main.py
resourcespace_cli/output.py
resourcespace_cli/api/__init__.py
resourcespace_cli/api/resources.py
resourcespace_cli/api/search.py
resourcespace_cli/api/types.py
resourcespace_cli/api/upload.py
resourcespace_cli/commands/__init__.py
resourcespace_cli/commands/collections.py
resourcespace_cli/commands/config.py
resourcespace_cli/commands/download.py
resourcespace_cli/commands/info.py
resourcespace_cli/commands/search.py
resourcespace_cli/commands/types.py
resourcespace_cli/commands/upload.py
resourcespace_cli/utils/__init__.py
resourcespace_cli/utils/errors.py
resourcespace_cli/utils/files.py
resourcespace_cli/utils/validation.py
resourcespace_cli-0.1.2.dist-info/METADATA
resourcespace_cli-0.1.2.dist-info/WHEEL
resourcespace_cli-0.1.2.dist-info/entry_points.txt
resourcespace_cli-0.1.2.dist-info/licenses/LICENSE
resourcespace_cli-0.1.2.dist-info/RECORD
