Metadata-Version: 2.4
Name: resourcespace-cli
Version: 0.1.2
Summary: Command-line tool for interacting with ResourceSpace
Project-URL: Homepage, https://github.com/TidalStudio/ResourceSpace-CLI
Project-URL: Repository, https://github.com/TidalStudio/ResourceSpace-CLI
Author: TidalStudio
License-Expression: MIT
License-File: LICENSE
Keywords: cli,dam,digital-asset-management,resourcespace
Classifier: Development Status :: 3 - Alpha
Classifier: Environment :: Console
Classifier: Intended Audience :: Developers
Classifier: License :: OSI Approved :: MIT License
Classifier: Programming Language :: Python :: 3
Classifier: Programming Language :: Python :: 3.11
Classifier: Programming Language :: Python :: 3.12
Requires-Python: >=3.11
Requires-Dist: click>=8.1.0
Requires-Dist: httpx>=0.27.0
Requires-Dist: pydantic>=2.0.0
Requires-Dist: python-dotenv>=1.0.0
Requires-Dist: rich>=13.0.0
Provides-Extra: dev
Requires-Dist: build>=1.0.0; extra == 'dev'
Requires-Dist: mypy>=1.13.0; extra == 'dev'
Requires-Dist: ruff>=0.8.0; extra == 'dev'
Requires-Dist: twine>=5.0.0; extra == 'dev'
Provides-Extra: test
Requires-Dist: pytest-cov>=4.1.0; extra == 'test'
Requires-Dist: pytest-httpx>=0.30.0; extra == 'test'
Requires-Dist: pytest-mock>=3.12.0; extra == 'test'
Requires-Dist: pytest>=8.0.0; extra == 'test'
